<refinement-definitions>        <refinement-definition type="attribute" bucket-type="none" attribute-id="FiltreBoucles" system="false">            <display-name xml:lang="x-default">Boucle</display-name>            <display-name xml:lang="fr-FR">Boucle</display-name>            <display-name xml:lang="it-IT">Riccio</display-name>            <display-name xml:lang="nl-NL">Type krul</display-name>            <value-set>search-result</value-set>            <sort-mode>value-name</sort-mode>            <sort-direction>ascending</sort-direction>            <cutoff-threshold>30</cutoff-threshold>        </refinement-definition>        <refinement-definition type="attribute" bucket-type="none" attribute-id="FiltreFonctions" system="false">            <display-name xml:lang="x-default">Fonction</display-name>            <display-name xml:lang="fr-FR">Fonction</display-name>            <display-name xml:lang="it-IT">Funzioni</display-name>            <display-name xml:lang="nl-NL">Functies</display-name>            <value-set>search-result</value-set>            <sort-mode>value-name</sort-mode>            <sort-direction>ascending</sort-direction>            <cutoff-threshold>30</cutoff-threshold>        </refinement-definition>        <refinement-definition type="attribute" bucket-type="none" attribute-id="FiltreSensDeBouclage" system="false">            <display-name xml:lang="x-default">Sens de Bouclage</display-name>            <display-name xml:lang="fr-FR">Sens De Bouclage</display-name>            <display-name xml:lang="it-IT">Direzione del riccio</display-name>            <display-name xml:lang="nl-NL">Krulrichting</display-name>            <value-set>search-result</value-set>            <sort-mode>value-name</sort-mode>            <sort-direction>ascending</sort-direction>            <cutoff-threshold>30</cutoff-threshold>        </refinement-definition>        <blocked-refinement-definition type="category"/>        <blocked-refinement-definition type="price"/>    </refinement-definitions>


<refinement-definitions>        <refinement-definition type="attribute" bucket-type="none" attribute-id="FiltreVitesseDAir" system="false">            <display-name xml:lang="x-default">Vitesse d'air</display-name>            <display-name xml:lang="fr-FR">Vitesse d'air</display-name>            <display-name xml:lang="it-IT">Velocità dell'aria</display-name>            <display-name xml:lang="nl-NL">Luchtsnelheid</display-name>            <value-set>search-result</value-set>            <sort-mode>value-name</sort-mode>            <sort-direction>ascending</sort-direction>            <cutoff-threshold>30</cutoff-threshold>        </refinement-definition>        <refinement-definition type="attribute" bucket-type="none" attribute-id="FiltreFonctions" system="false">            <display-name xml:lang="x-default">Fonction</display-name>            <display-name xml:lang="fr-FR">Fonction</display-name>            <display-name xml:lang="it-IT">Funzioni</display-name>            <display-name xml:lang="nl-NL">Functies</display-name>            <value-set>search-result</value-set>            <sort-mode>value-name</sort-mode>            <sort-direction>ascending</sort-direction>            <cutoff-threshold>30</cutoff-threshold>        </refinement-definition>        <refinement-definition type="attribute" bucket-type="none" attribute-id="FiltreAccessoire" system="false">            <display-name xml:lang="x-default">Accessoire</display-name>            <display-name xml:lang="fr-FR">Accessoire</display-name>            <display-name xml:lang="it-IT">Accessori</display-name>            <display-name xml:lang="nl-NL">Accessoires</display-name>            <value-set>search-result</value-set>            <sort-mode>value-name</sort-mode>            <sort-direction>ascending</sort-direction>            <cutoff-threshold>30</cutoff-threshold>        </refinement-definition>        <refinement-definition type="attribute" bucket-type="none" attribute-id="FiltreBesoins" system="false">            <display-name xml:lang="x-default">Besoin</display-name>            <display-name xml:lang="fr-FR">Besoin</display-name>            <display-name xml:lang="it-IT">Bisogno</display-name>            <display-name xml:lang="nl-NL">Eigenschappen</display-name>            <value-set>search-result</value-set>            <sort-mode>value-name</sort-mode>            <sort-direction>ascending</sort-direction>            <cutoff-threshold>30</cutoff-threshold>        </refinement-definition>        <blocked-refinement-definition type="category"/>        <blocked-refinement-definition type="price"/>    </refinement-definitions>



<refinement-definitions>        <refinement-definition type="attribute" bucket-type="none" attribute-id="FiltreFonctions" system="false">            <display-name xml:lang="x-default">Fonction</display-name>            <display-name xml:lang="fr-FR">Fonction</display-name>            <display-name xml:lang="it-IT">Funzioni</display-name>            <display-name xml:lang="nl-NL">Functies</display-name>            <value-set>search-result</value-set>            <sort-mode>value-name</sort-mode>            <sort-direction>ascending</sort-direction>            <cutoff-threshold>30</cutoff-threshold>        </refinement-definition>        <refinement-definition type="attribute" bucket-type="none" attribute-id="FiltreBrosse" system="false">            <display-name xml:lang="x-default">Brosse</display-name>            <display-name xml:lang="fr-FR">Brosse</display-name>            <display-name xml:lang="it-IT">Spazzola </display-name>            <display-name xml:lang="nl-NL">Borstelpinnen</display-name>            <value-set>search-result</value-set>            <sort-mode>value-name</sort-mode>            <sort-direction>ascending</sort-direction>            <cutoff-threshold>30</cutoff-threshold>        </refinement-definition>        <refinement-definition type="attribute" bucket-type="none" attribute-id="FiltreAccessoire" system="false">            <display-name xml:lang="x-default">Accessoire</display-name>            <display-name xml:lang="fr-FR">Accessoire</display-name>            <display-name xml:lang="it-IT">Accessori</display-name>            <display-name xml:lang="nl-NL">Accessoires</display-name>            <value-set>search-result</value-set>            <sort-mode>value-name</sort-mode>            <sort-direction>ascending</sort-direction>            <cutoff-threshold>30</cutoff-threshold>        </refinement-definition>        <blocked-refinement-definition type="category"/>        <blocked-refinement-definition type="price"/>    </refinement-definitions>



<refinement-definitions>        <refinement-definition type="attribute" bucket-type="none" attribute-id="FiltreBesoins" system="false">            <display-name xml:lang="x-default">Eigenschappen</display-name>            <display-name xml:lang="nl-NL">Eigenschappen</display-name>            <value-set>search-result</value-set>            <sort-mode>value-name</sort-mode>            <sort-direction>ascending</sort-direction>            <cutoff-threshold>5</cutoff-threshold>        </refinement-definition>        <blocked-refinement-definition type="category"/>        <blocked-refinement-definition type="price"/>    </refinement-definitions>



<refinement-definitions>        <refinement-definition type="attribute" bucket-type="none" attribute-id="FiltreBoucles" system="false">            <display-name xml:lang="x-default">Boucle</display-name>            <display-name xml:lang="fr-FR">Boucle</display-name>            <display-name xml:lang="it-IT">Riccio</display-name>            <display-name xml:lang="nl-NL">Type krul</display-name>            <value-set>search-result</value-set>            <sort-mode>value-name</sort-mode>            <sort-direction>ascending</sort-direction>            <cutoff-threshold>30</cutoff-threshold>        </refinement-definition>        <refinement-definition type="attribute" bucket-type="none" attribute-id="FiltreAccessoire" system="false">            <display-name xml:lang="x-default">Accessoire</display-name>            <display-name xml:lang="fr-FR">Accessoire</display-name>            <display-name xml:lang="it-IT">Accessori</display-name>            <display-name xml:lang="nl-NL">Accessoires</display-name>            <value-set>search-result</value-set>            <sort-mode>value-name</sort-mode>            <sort-direction>ascending</sort-direction>            <cutoff-threshold>30</cutoff-threshold>        </refinement-definition>        <blocked-refinement-definition type="category"/>    </refinement-definitions>




<refinement-definitions>        <blocked-refinement-definition type="attribute" attribute-id="sheets" system="false"/>        <blocked-refinement-definition type="attribute" attribute-id="isNew" system="false"/>        <blocked-refinement-definition type="price"/>        <blocked-refinement-definition type="attribute" attribute-id="refinementColor" system="false"/>        <blocked-refinement-definition type="category"/>    </refinement-definitions>




<refinement-definitions>        <refinement-definition type="attribute" bucket-type="none" attribute-id="FiltreBesoins" system="false">            <display-name xml:lang="x-default">Besoin</display-name>            <display-name xml:lang="fr-FR">Besoin</display-name>            <display-name xml:lang="it-IT">Bisogno</display-name>            <display-name xml:lang="nl-NL">Eigenschappen</display-name>            <value-set>search-result</value-set>            <sort-mode>value-name</sort-mode>            <sort-direction>ascending</sort-direction>            <cutoff-threshold>30</cutoff-threshold>        </refinement-definition>        <refinement-definition type="attribute" bucket-type="none" attribute-id="FiltreBoucles" system="false">            <display-name xml:lang="x-default">Boucle</display-name>            <display-name xml:lang="fr-FR">Boucle</display-name>            <display-name xml:lang="it-IT">Riccio</display-name>            <display-name xml:lang="nl-NL">Type krul</display-name>            <value-set>search-result</value-set>            <sort-mode>value-name</sort-mode>            <sort-direction>ascending</sort-direction>            <cutoff-threshold>30</cutoff-threshold>        </refinement-definition>        <refinement-definition type="attribute" bucket-type="none" attribute-id="FiltreAccessoire" system="false">            <display-name xml:lang="x-default">Accessoire</display-name>            <display-name xml:lang="fr-FR">Accessoire</display-name>            <display-name xml:lang="it-IT">Accessori</display-name>            <display-name xml:lang="nl-NL">Accessoires</display-name>            <value-set>search-result</value-set>            <sort-mode>value-name</sort-mode>            <sort-direction>ascending</sort-direction>            <cutoff-threshold>30</cutoff-threshold>        </refinement-definition>        <blocked-refinement-definition type="category"/>        <blocked-refinement-definition type="price"/>    </refinement-definitions>



<refinement-definitions>        <refinement-definition type="attribute" bucket-type="none" attribute-id="FiltreFonctions" system="false">            <display-name xml:lang="x-default">Fonction</display-name>            <display-name xml:lang="fr-FR">Fonction</display-name>            <display-name xml:lang="it-IT">Funzioni</display-name>            <display-name xml:lang="nl-NL">Functies</display-name>            <value-set>search-result</value-set>            <sort-mode>value-name</sort-mode>            <sort-direction>ascending</sort-direction>            <cutoff-threshold>30</cutoff-threshold>        </refinement-definition>        <refinement-definition type="attribute" bucket-type="none" attribute-id="FiltreLongueurDeCheveux" system="false">            <display-name xml:lang="x-default">Longueur des cheveux</display-name>            <display-name xml:lang="fr-FR">Longueur des cheveux</display-name>            <display-name xml:lang="it-IT">Lunghezza dei capelli</display-name>            <display-name xml:lang="nl-NL">Haarlengte</display-name>            <value-set>search-result</value-set>            <sort-mode>value-name</sort-mode>            <sort-direction>ascending</sort-direction>            <cutoff-threshold>30</cutoff-threshold>        </refinement-definition>        <refinement-definition type="attribute" bucket-type="none" attribute-id="FiltreTypeDeCheveux" system="false">            <display-name xml:lang="x-default">Type de Cheveux</display-name>            <display-name xml:lang="fr-FR">Type de Cheveux</display-name>            <display-name xml:lang="it-IT">Tipo di capelli</display-name>            <display-name xml:lang="nl-NL">Haartype</display-name>            <value-set>search-result</value-set>            <sort-mode>value-name</sort-mode>            <sort-direction>ascending</sort-direction>            <cutoff-threshold>30</cutoff-threshold>        </refinement-definition>        <refinement-definition type="attribute" bucket-type="none" attribute-id="FiltreAccessoire" system="false">            <display-name xml:lang="x-default">Accessoire</display-name>            <display-name xml:lang="fr-FR">Accessoire</display-name>            <display-name xml:lang="it-IT">Accessori</display-name>            <display-name xml:lang="nl-NL">Accessoire</display-name>            <value-set>search-result</value-set>            <sort-mode>value-name</sort-mode>            <sort-direction>ascending</sort-direction>            <cutoff-threshold>30</cutoff-threshold>        </refinement-definition>        <blocked-refinement-definition type="category"/>        <blocked-refinement-definition type="price"/>    </refinement-definitions>



<refinement-definitions>        <blocked-refinement-definition type="category"/>    </refinement-definitions>





<refinement-definitions>        <refinement-definition type="attribute" bucket-type="none" attribute-id="FiltreBesoins" system="false">            <display-name xml:lang="fr-FR">Besoins</display-name>            <display-name xml:lang="it-IT">Bisogni</display-name>            <display-name xml:lang="nl-NL">Eigenschappen</display-name>            <value-set>search-result</value-set>            <sort-mode>value-name</sort-mode>            <sort-direction>ascending</sort-direction>            <cutoff-threshold>5</cutoff-threshold>        </refinement-definition>        <refinement-definition type="attribute" bucket-type="none" attribute-id="FiltreTypeDeCheveux" system="false">            <display-name xml:lang="fr-FR">Type de cheveux</display-name>            <display-name xml:lang="it-IT">Tipo di capelli</display-name>            <display-name xml:lang="nl-NL">Haartype</display-name>            <value-set>search-result</value-set>            <sort-mode>value-name</sort-mode>            <sort-direction>ascending</sort-direction>            <cutoff-threshold>5</cutoff-threshold>        </refinement-definition>        <refinement-definition type="attribute" bucket-type="none" attribute-id="FiltrePicotsPoils" system="false">            <display-name xml:lang="fr-FR">Picots/Poils</display-name>            <display-name xml:lang="it-IT">Setole</display-name>            <display-name xml:lang="nl-NL">Borstelpinnen</display-name>            <value-set>search-result</value-set>            <sort-mode>value-name</sort-mode>            <sort-direction>ascending</sort-direction>            <cutoff-threshold>5</cutoff-threshold>        </refinement-definition>        <refinement-definition type="attribute" bucket-type="none" attribute-id="FiltreOptions" system="false">            <display-name xml:lang="fr-FR">Option</display-name>            <display-name xml:lang="it-IT">Opzione</display-name>            <display-name xml:lang="nl-NL">Opties</display-name>            <value-set>search-result</value-set>            <sort-mode>value-name</sort-mode>            <sort-direction>ascending</sort-direction>            <cutoff-threshold>5</cutoff-threshold>        </refinement-definition>        <blocked-refinement-definition type="category"/>        <blocked-refinement-definition type="price"/>    </refinement-definitions>




<refinement-definitions>        <refinement-definition type="attribute" bucket-type="none" attribute-id="FiltreCollections" system="false">            <display-name xml:lang="x-default">Collection</display-name>            <display-name xml:lang="fr-FR">Collection</display-name>            <display-name xml:lang="it-IT">Gamma</display-name>            <display-name xml:lang="nl-NL">Collectie</display-name>            <value-set>search-result</value-set>            <sort-mode>value-name</sort-mode>            <sort-direction>ascending</sort-direction>            <cutoff-threshold>20</cutoff-threshold>        </refinement-definition>        <blocked-refinement-definition type="category"/>        <blocked-refinement-definition type="price"/>    </refinement-definitions>






<refinement-definitions>        <refinement-definition type="attribute" bucket-type="none" attribute-id="FiltreBesoins" system="false">            <display-name xml:lang="x-default">Besoin</display-name>            <display-name xml:lang="fr-FR">Besoin</display-name>            <display-name xml:lang="it-IT">Bisogno</display-name>            <display-name xml:lang="nl-NL">Eigenschappen</display-name>            <value-set>search-result</value-set>            <sort-mode>value-name</sort-mode>            <sort-direction>ascending</sort-direction>            <cutoff-threshold>30</cutoff-threshold>        </refinement-definition>        <refinement-definition type="attribute" bucket-type="none" attribute-id="FiltreSystemes" system="false">            <display-name xml:lang="x-default">Système</display-name>            <display-name xml:lang="fr-FR">Système</display-name>            <display-name xml:lang="it-IT">Sistema</display-name>            <display-name xml:lang="nl-NL">Type kop</display-name>            <value-set>search-result</value-set>            <sort-mode>value-name</sort-mode>            <sort-direction>ascending</sort-direction>            <cutoff-threshold>30</cutoff-threshold>        </refinement-definition>        <refinement-definition type="attribute" bucket-type="none" attribute-id="FiltreOptions" system="false">            <display-name xml:lang="x-default">Options</display-name>            <display-name xml:lang="fr-FR">Options</display-name>            <display-name xml:lang="it-IT">Opzioni</display-name>            <display-name xml:lang="nl-NL">Opties</display-name>            <value-set>search-result</value-set>            <sort-mode>value-name</sort-mode>            <sort-direction>ascending</sort-direction>            <cutoff-threshold>30</cutoff-threshold>        </refinement-definition>        <refinement-definition type="attribute" bucket-type="none" attribute-id="FiltreAccessoire" system="false">            <display-name xml:lang="x-default">Accessoires</display-name>            <display-name xml:lang="fr-FR">Accessoires</display-name>            <display-name xml:lang="it-IT">Accessori</display-name>            <display-name xml:lang="nl-NL">Accessoires</display-name>            <value-set>search-result</value-set>            <sort-mode>value-name</sort-mode>            <sort-direction>ascending</sort-direction>            <cutoff-threshold>30</cutoff-threshold>        </refinement-definition>        <blocked-refinement-definition type="category"/>    </refinement-definitions>



<refinement-definitions>        <refinement-definition type="attribute" bucket-type="none" attribute-id="FiltreFormat" system="false">            <display-name xml:lang="x-default">Format</display-name>            <display-name xml:lang="fr-FR">Format</display-name>            <display-name xml:lang="it-IT">Formato</display-name>            <display-name xml:lang="nl-NL">Formaat</display-name>            <value-set>search-result</value-set>            <sort-mode>value-name</sort-mode>            <sort-direction>ascending</sort-direction>            <cutoff-threshold>30</cutoff-threshold>        </refinement-definition>        <refinement-definition type="attribute" bucket-type="none" attribute-id="FiltreNombreDeFlash" system="false">            <display-name xml:lang="x-default">Nombre de Flash</display-name>            <display-name xml:lang="fr-FR">Nombre de Flash</display-name>            <display-name xml:lang="it-IT">Numero di Flash</display-name>            <display-name xml:lang="nl-NL">Aantal flitsen</display-name>            <value-set>search-result</value-set>            <sort-mode>value-name</sort-mode>            <sort-direction>ascending</sort-direction>            <cutoff-threshold>30</cutoff-threshold>        </refinement-definition>        <refinement-definition type="attribute" bucket-type="none" attribute-id="FiltreFonctions" system="false">            <display-name xml:lang="x-default">Fonction</display-name>            <display-name xml:lang="fr-FR">Fonction</display-name>            <display-name xml:lang="it-IT">Funzioni</display-name>            <display-name xml:lang="nl-NL">Functies</display-name>            <value-set>search-result</value-set>            <sort-mode>value-name</sort-mode>            <sort-direction>ascending</sort-direction>            <cutoff-threshold>30</cutoff-threshold>        </refinement-definition>        <refinement-definition type="attribute" bucket-type="none" attribute-id="FiltreOptions" system="false">            <display-name xml:lang="x-default">Options</display-name>            <display-name xml:lang="fr-FR">Options</display-name>            <display-name xml:lang="it-IT">Opzioni</display-name>            <display-name xml:lang="nl-NL">Opties</display-name>            <value-set>search-result</value-set>            <sort-mode>value-name</sort-mode>            <sort-direction>ascending</sort-direction>            <cutoff-threshold>30</cutoff-threshold>        </refinement-definition>        <blocked-refinement-definition type="category"/>    </refinement-definitions>





<refinement-definitions>        <blocked-refinement-definition type="category"/>    </refinement-definitions>



<refinement-definitions>        <refinement-definition type="attribute" bucket-type="none" attribute-id="FiltreFonctions" system="false">            <display-name xml:lang="x-default">Fonctions</display-name>            <display-name xml:lang="fr-FR">Fonctions</display-name>            <display-name xml:lang="it-IT">Funzioni</display-name>            <display-name xml:lang="nl-NL">Functies</display-name>            <value-set>search-result</value-set>            <sort-mode>value-name</sort-mode>            <sort-direction>ascending</sort-direction>            <cutoff-threshold>30</cutoff-threshold>        </refinement-definition>        <blocked-refinement-definition type="category"/>    </refinement-definitions>




<refinement-definitions>        <refinement-definition type="attribute" bucket-type="none" attribute-id="FiltreFonctions" system="false">            <display-name xml:lang="x-default">Fonctions</display-name>            <display-name xml:lang="fr-FR">Fonctions</display-name>            <display-name xml:lang="it-IT">Funzioni</display-name>            <display-name xml:lang="nl-NL">Functies</display-name>            <value-set>search-result</value-set>            <sort-mode>value-name</sort-mode>            <sort-direction>ascending</sort-direction>            <cutoff-threshold>30</cutoff-threshold>        </refinement-definition>        <refinement-definition type="attribute" bucket-type="none" attribute-id="FiltreOptions" system="false">            <display-name xml:lang="x-default">Options</display-name>            <display-name xml:lang="fr-FR">Options</display-name>            <display-name xml:lang="it-IT">Opzioni</display-name>            <display-name xml:lang="nl-NL">Opties</display-name>            <value-set>search-result</value-set>            <sort-mode>value-name</sort-mode>            <sort-direction>ascending</sort-direction>            <cutoff-threshold>30</cutoff-threshold>        </refinement-definition>        <blocked-refinement-definition type="category"/>    </refinement-definitions>



<refinement-definitions>        <refinement-definition type="attribute" bucket-type="none" attribute-id="FiltreCollections" system="false">            <display-name xml:lang="x-default">Collections</display-name>            <display-name xml:lang="fr-FR">Collections</display-name>            <display-name xml:lang="it-IT">Collezioni</display-name>            <display-name xml:lang="nl-NL">Collectie</display-name>            <value-set>search-result</value-set>            <sort-mode>value-name</sort-mode>            <sort-direction>ascending</sort-direction>            <cutoff-threshold>30</cutoff-threshold>        </refinement-definition>        <blocked-refinement-definition type="category"/>    </refinement-definitions>



<refinement-definitions>        <blocked-refinement-definition type="category"/>    </refinement-definitions>




<refinement-definitions>        <refinement-definition type="attribute" bucket-type="none" attribute-id="brand" system="true">            <display-name xml:lang="x-default">Brand</display-name>            <display-name xml:lang="nl-NL">Merk</display-name>            <value-set>search-result</value-set>            <sort-mode>value-name</sort-mode>            <sort-direction>ascending</sort-direction>            <cutoff-threshold>5</cutoff-threshold>        </refinement-definition>        <blocked-refinement-definition type="attribute" attribute-id="refinementColor" system="false"/>        <blocked-refinement-definition type="attribute" attribute-id="size" system="false"/>    </refinement-definitions>





<refinement-definitions>        <refinement-definition type="attribute" bucket-type="none" attribute-id="FiltreHauteurDecoupe" system="false">            <display-name xml:lang="x-default">Hauteur de Coupe</display-name>            <display-name xml:lang="fr-FR">Hauteur de Coupe</display-name>            <display-name xml:lang="it-IT">Altezza di taglio</display-name>            <display-name xml:lang="nl-NL">Lengte instellingen</display-name>            <value-set>search-result</value-set>            <sort-mode>value-name</sort-mode>            <sort-direction>ascending</sort-direction>            <cutoff-threshold>30</cutoff-threshold>        </refinement-definition>        <refinement-definition type="attribute" bucket-type="none" attribute-id="FiltrePrecisions" system="false">            <display-name xml:lang="x-default">Précisions</display-name>            <display-name xml:lang="fr-FR">Précisions</display-name>            <display-name xml:lang="it-IT">Precisione</display-name>            <display-name xml:lang="nl-NL">Precisie instelling</display-name>            <value-set>search-result</value-set>            <sort-mode>value-name</sort-mode>            <sort-direction>ascending</sort-direction>            <cutoff-threshold>30</cutoff-threshold>        </refinement-definition>        <refinement-definition type="attribute" bucket-type="none" attribute-id="FiltreReglageHauteur" system="false">            <display-name xml:lang="x-default">Réglage Hauteur</display-name>            <display-name xml:lang="fr-FR">Réglage Hauteur</display-name>            <display-name xml:lang="it-IT">Regolazione Altezza</display-name>            <display-name xml:lang="nl-NL">Bediening hoogte instelling</display-name>            <value-set>search-result</value-set>            <sort-mode>value-name</sort-mode>            <sort-direction>ascending</sort-direction>            <cutoff-threshold>30</cutoff-threshold>        </refinement-definition>        <refinement-definition type="attribute" bucket-type="none" attribute-id="FiltreFonctions" system="false">            <display-name xml:lang="x-default">Fonction</display-name>            <display-name xml:lang="fr-FR">Fonction</display-name>            <display-name xml:lang="it-IT">Funzioni</display-name>            <display-name xml:lang="nl-NL">Functies</display-name>            <value-set>search-result</value-set>            <sort-mode>value-name</sort-mode>            <sort-direction>ascending</sort-direction>            <cutoff-threshold>30</cutoff-threshold>        </refinement-definition>        <refinement-definition type="attribute" bucket-type="none" attribute-id="FiltreUtilisations" system="false">            <display-name xml:lang="x-default">Utilisation</display-name>            <display-name xml:lang="fr-FR">Utilisation</display-name>            <display-name xml:lang="it-IT">Utilizzo</display-name>            <display-name xml:lang="nl-NL">Gebruik</display-name>            <value-set>search-result</value-set>            <sort-mode>value-name</sort-mode>            <sort-direction>ascending</sort-direction>            <cutoff-threshold>30</cutoff-threshold>        </refinement-definition>        <refinement-definition type="attribute" bucket-type="none" attribute-id="FiltreAccessoire" system="false">            <display-name xml:lang="x-default">Accessoires</display-name>            <display-name xml:lang="fr-FR">Accessoires</display-name>            <display-name xml:lang="it-IT">Accessori</display-name>            <display-name xml:lang="nl-NL">Accessoires</display-name>            <value-set>search-result</value-set>            <sort-mode>value-name</sort-mode>            <sort-direction>ascending</sort-direction>            <cutoff-threshold>30</cutoff-threshold>        </refinement-definition>        <blocked-refinement-definition type="category"/>        <blocked-refinement-definition type="price"/>    </refinement-definitions>





<refinement-definitions>        <refinement-definition type="attribute" bucket-type="none" attribute-id="FiltreBesoins" system="false">            <display-name xml:lang="x-default">Besoin</display-name>            <display-name xml:lang="fr-FR">Besoin</display-name>            <display-name xml:lang="it-IT">Bisogno</display-name>            <display-name xml:lang="nl-NL">Eigenschappen</display-name>            <value-set>search-result</value-set>            <sort-mode>value-name</sort-mode>            <sort-direction>ascending</sort-direction>            <cutoff-threshold>30</cutoff-threshold>        </refinement-definition>        <blocked-refinement-definition type="category"/>        <blocked-refinement-definition type="attribute" attribute-id="brand" system="true"/>        <blocked-refinement-definition type="price"/>    </refinement-definitions>



<refinement-definitions>        <refinement-definition type="attribute" bucket-type="none" attribute-id="FiltreUsages" system="false">            <display-name xml:lang="x-default">Usage</display-name>            <display-name xml:lang="fr-FR">Usage</display-name>            <display-name xml:lang="it-IT">Utilizzo</display-name>            <display-name xml:lang="nl-NL">Gebruik</display-name>            <value-set>search-result</value-set>            <sort-mode>value-name</sort-mode>            <sort-direction>ascending</sort-direction>            <cutoff-threshold>30</cutoff-threshold>        </refinement-definition>        <refinement-definition type="attribute" bucket-type="none" attribute-id="FiltreOptions" system="false">            <display-name xml:lang="x-default">Options</display-name>            <display-name xml:lang="fr-FR">Options</display-name>            <display-name xml:lang="it-IT">Opzioni</display-name>            <display-name xml:lang="nl-NL">Opties</display-name>            <value-set>search-result</value-set>            <sort-mode>value-name</sort-mode>            <sort-direction>ascending</sort-direction>            <cutoff-threshold>30</cutoff-threshold>        </refinement-definition>        <refinement-definition type="attribute" bucket-type="none" attribute-id="FiltreFonctions" system="false">            <display-name xml:lang="x-default">Fonctions</display-name>            <display-name xml:lang="fr-FR">Fonctions</display-name>            <display-name xml:lang="it-IT">Funzioni</display-name>            <display-name xml:lang="nl-NL">Functies</display-name>            <value-set>search-result</value-set>            <sort-mode>value-name</sort-mode>            <sort-direction>ascending</sort-direction>            <cutoff-threshold>30</cutoff-threshold>        </refinement-definition>        <refinement-definition type="attribute" bucket-type="none" attribute-id="FiltreAccessoire" system="false">            <display-name xml:lang="x-default">Accessoires</display-name>            <display-name xml:lang="fr-FR">Accessoires</display-name>            <display-name xml:lang="it-IT">Accessori</display-name>            <display-name xml:lang="nl-NL">Accessoires</display-name>            <value-set>search-result</value-set>            <sort-mode>value-name</sort-mode>            <sort-direction>ascending</sort-direction>            <cutoff-threshold>30</cutoff-threshold>        </refinement-definition>        <blocked-refinement-definition type="category"/>        <blocked-refinement-definition type="price"/>    </refinement-definitions>



<refinement-definitions>        <blocked-refinement-definition type="category"/>    </refinement-definitions>





<refinement-definitions>        <refinement-definition type="attribute" bucket-type="none" attribute-id="FiltreHauteurDecoupe" system="false">            <display-name xml:lang="x-default">Hauteur de Coupe</display-name>            <display-name xml:lang="fr-FR">Hauteur de Coupe</display-name>            <display-name xml:lang="it-IT">Altezza di taglio</display-name>            <display-name xml:lang="nl-NL">Lengte instellingen</display-name>            <value-set>search-result</value-set>            <sort-mode>value-name</sort-mode>            <sort-direction>ascending</sort-direction>            <cutoff-threshold>30</cutoff-threshold>        </refinement-definition>        <refinement-definition type="attribute" bucket-type="none" attribute-id="FiltrePrecisions" system="false">            <display-name xml:lang="x-default">Précisions</display-name>            <display-name xml:lang="fr-FR">Précisions</display-name>            <display-name xml:lang="it-IT">Precisione</display-name>            <display-name xml:lang="nl-NL">Precisie instelling</display-name>            <value-set>search-result</value-set>            <sort-mode>value-name</sort-mode>            <sort-direction>ascending</sort-direction>            <cutoff-threshold>30</cutoff-threshold>        </refinement-definition>        <refinement-definition type="attribute" bucket-type="none" attribute-id="FiltreMoteurs" system="false">            <display-name xml:lang="x-default">Moteur</display-name>            <display-name xml:lang="fr-FR">Moteur</display-name>            <display-name xml:lang="it-IT">Motore</display-name>            <display-name xml:lang="nl-NL">Motor</display-name>            <value-set>search-result</value-set>            <sort-mode>value-name</sort-mode>            <sort-direction>ascending</sort-direction>            <cutoff-threshold>30</cutoff-threshold>        </refinement-definition>        <refinement-definition type="attribute" bucket-type="none" attribute-id="FiltreFonctions" system="false">            <display-name xml:lang="x-default">Fonction</display-name>            <display-name xml:lang="fr-FR">Fonction</display-name>            <display-name xml:lang="it-IT">Funzioni</display-name>            <display-name xml:lang="nl-NL">Functies</display-name>            <value-set>search-result</value-set>            <sort-mode>value-name</sort-mode>            <sort-direction>ascending</sort-direction>            <cutoff-threshold>30</cutoff-threshold>        </refinement-definition>        <refinement-definition type="attribute" bucket-type="none" attribute-id="FiltreUtilisations" system="false">            <display-name xml:lang="x-default">Utilisation</display-name>            <display-name xml:lang="fr-FR">Utilisation</display-name>            <display-name xml:lang="it-IT">Utilizzo</display-name>            <display-name xml:lang="nl-NL">Gebruik</display-name>            <value-set>search-result</value-set>            <sort-mode>value-name</sort-mode>            <sort-direction>ascending</sort-direction>            <cutoff-threshold>30</cutoff-threshold>        </refinement-definition>        <refinement-definition type="attribute" bucket-type="none" attribute-id="FiltreAccessoire" system="false">            <display-name xml:lang="x-default">Accessoires</display-name>            <display-name xml:lang="fr-FR">Accessoires</display-name>            <display-name xml:lang="it-IT">Accessori</display-name>            <display-name xml:lang="nl-NL">Accessoires</display-name>            <value-set>search-result</value-set>            <sort-mode>value-name</sort-mode>            <sort-direction>ascending</sort-direction>            <cutoff-threshold>30</cutoff-threshold>        </refinement-definition>        <blocked-refinement-definition type="category"/>    </refinement-definitions>



<refinement-definitions>        <refinement-definition type="attribute" bucket-type="none" attribute-id="FiltreUsages" system="false">            <display-name xml:lang="x-default">Usage</display-name>            <display-name xml:lang="fr-FR">Usage</display-name>            <display-name xml:lang="it-IT">Utilizzo</display-name>            <display-name xml:lang="nl-NL">Gebruik</display-name>            <value-set>search-result</value-set>            <sort-mode>value-name</sort-mode>            <sort-direction>ascending</sort-direction>            <cutoff-threshold>30</cutoff-threshold>        </refinement-definition>        <refinement-definition type="attribute" bucket-type="none" attribute-id="FiltreOptions" system="false">            <display-name xml:lang="x-default">Options</display-name>            <display-name xml:lang="fr-FR">Options</display-name>            <display-name xml:lang="it-IT">Opzioni</display-name>            <display-name xml:lang="nl-NL">Opties</display-name>            <value-set>search-result</value-set>            <sort-mode>value-name</sort-mode>            <sort-direction>ascending</sort-direction>            <cutoff-threshold>30</cutoff-threshold>        </refinement-definition>        <refinement-definition type="attribute" bucket-type="none" attribute-id="FiltreFonctions" system="false">            <display-name xml:lang="x-default">Fonction</display-name>            <display-name xml:lang="fr-FR">Fonction</display-name>            <display-name xml:lang="it-IT">Funzioni</display-name>            <display-name xml:lang="nl-NL">Functies</display-name>            <value-set>search-result</value-set>            <sort-mode>value-name</sort-mode>            <sort-direction>ascending</sort-direction>            <cutoff-threshold>30</cutoff-threshold>        </refinement-definition>        <refinement-definition type="attribute" bucket-type="none" attribute-id="FiltreAccessoire" system="false">            <display-name xml:lang="x-default">Accessoire</display-name>            <display-name xml:lang="fr-FR">Accessoire</display-name>            <display-name xml:lang="it-IT">Accessori</display-name>            <display-name xml:lang="nl-NL">Accessoires</display-name>            <value-set>search-result</value-set>            <sort-mode>value-name</sort-mode>            <sort-direction>ascending</sort-direction>            <cutoff-threshold>30</cutoff-threshold>        </refinement-definition>        <blocked-refinement-definition type="category"/>    </refinement-definitions>





<refinement-definitions>        <refinement-definition type="attribute" bucket-type="none" attribute-id="FiltreUsages" system="false">            <display-name xml:lang="x-default">Usage</display-name>            <display-name xml:lang="fr-FR">Usage</display-name>            <display-name xml:lang="it-IT">Utilizzo</display-name>            <display-name xml:lang="nl-NL">Gebruik</display-name>            <value-set>search-result</value-set>            <sort-mode>value-name</sort-mode>            <sort-direction>ascending</sort-direction>            <cutoff-threshold>30</cutoff-threshold>        </refinement-definition>        <refinement-definition type="attribute" bucket-type="none" attribute-id="FiltreOptions" system="false">            <display-name xml:lang="x-default">Options</display-name>            <display-name xml:lang="fr-FR">Options</display-name>            <display-name xml:lang="it-IT">Opzioni</display-name>            <display-name xml:lang="nl-NL">Opties</display-name>            <value-set>search-result</value-set>            <sort-mode>value-name</sort-mode>            <sort-direction>ascending</sort-direction>            <cutoff-threshold>30</cutoff-threshold>        </refinement-definition>        <refinement-definition type="attribute" bucket-type="none" attribute-id="FiltreFonctions" system="false">            <display-name xml:lang="x-default">Fonction</display-name>            <display-name xml:lang="fr-FR">Fonction</display-name>            <display-name xml:lang="it-IT">Funzioni</display-name>            <display-name xml:lang="nl-NL">Functies</display-name>            <value-set>search-result</value-set>            <sort-mode>value-name</sort-mode>            <sort-direction>ascending</sort-direction>            <cutoff-threshold>30</cutoff-threshold>        </refinement-definition>        <refinement-definition type="attribute" bucket-type="none" attribute-id="FiltreAccessoire" system="false">            <display-name xml:lang="x-default">Accessoire</display-name>            <display-name xml:lang="fr-FR">Accessoire</display-name>            <display-name xml:lang="it-IT">Accessori</display-name>            <display-name xml:lang="nl-NL">Accessoire</display-name>            <value-set>search-result</value-set>            <sort-mode>value-name</sort-mode>            <sort-direction>ascending</sort-direction>            <cutoff-threshold>30</cutoff-threshold>        </refinement-definition>        <blocked-refinement-definition type="category"/>    </refinement-definitions>



<refinement-definitions>        <refinement-definition type="attribute" bucket-type="none" attribute-id="FiltreOptions" system="false">            <display-name xml:lang="x-default">Options</display-name>            <display-name xml:lang="fr-FR">Options</display-name>            <display-name xml:lang="it-IT">Opzioni</display-name>            <display-name xml:lang="nl-NL">Opties</display-name>            <value-set>search-result</value-set>            <sort-mode>value-name</sort-mode>            <sort-direction>ascending</sort-direction>            <cutoff-threshold>30</cutoff-threshold>        </refinement-definition>        <refinement-definition type="attribute" bucket-type="none" attribute-id="FiltreAccessoire" system="false">            <display-name xml:lang="x-default">Accessoires</display-name>            <display-name xml:lang="fr-FR">Accessoires</display-name>            <display-name xml:lang="it-IT">Accessori</display-name>            <display-name xml:lang="nl-NL">Accessoires</display-name>            <value-set>search-result</value-set>            <sort-mode>value-name</sort-mode>            <sort-direction>ascending</sort-direction>            <cutoff-threshold>30</cutoff-threshold>        </refinement-definition>        <blocked-refinement-definition type="category"/>    </refinement-definitions>





<refinement-definitions>        <refinement-definition type="attribute" bucket-type="none" attribute-id="FiltreStyle" system="false">            <display-name xml:lang="x-default">Style</display-name>            <display-name xml:lang="fr-FR">Style</display-name>            <display-name xml:lang="it-IT">Stile</display-name>            <display-name xml:lang="nl-NL">Stijl</display-name>            <value-set>search-result</value-set>            <sort-mode>value-name</sort-mode>            <sort-direction>ascending</sort-direction>            <cutoff-threshold>30</cutoff-threshold>        </refinement-definition>        <refinement-definition type="attribute" bucket-type="none" attribute-id="FiltreMatiere" system="false">            <display-name xml:lang="x-default">Matières</display-name>            <display-name xml:lang="fr-FR">Matières</display-name>            <display-name xml:lang="it-IT">Materie</display-name>            <display-name xml:lang="nl-NL">Materialen</display-name>            <value-set>search-result</value-set>            <sort-mode>value-name</sort-mode>            <sort-direction>ascending</sort-direction>            <cutoff-threshold>30</cutoff-threshold>        </refinement-definition>    </refinement-definitions>